LICENSE.txt
MANIFEST.in
README.md
description.md
setup.cfg
setup.py
data/stackmaster_testdataset.pk
figs/stack_example.png
figs/stackmaster_logo.png
notebooks/plot_stackmasterlogo.ipynb
notebooks/.ipynb_checkpoints/plot_stackmasterlogo-checkpoint.ipynb
stackmaster/__init__.py
stackmaster/core.py
stackmaster/utils.py
stackmaster.egg-info/PKG-INFO
stackmaster.egg-info/SOURCES.txt
stackmaster.egg-info/dependency_links.txt
stackmaster.egg-info/requires.txt
stackmaster.egg-info/top_level.txt