Metadata-Version: 2.1
Name: stackmaster
Version: 1.1.0
Summary: A collection of methods for data stacking
Home-page: https://github.com/xtyangpsp/StackMaster
Download-URL: https://github.com/xtyangpsp/StackMaster/archive/refs/tags/v1.1.0.tar.gz
Author: Xiaotao Yang
Author-email: stcyang@gmail.com
Maintainer: Xiaotao Yang
Maintainer-email: stcyang@gmail.com
License: MIT license
Keywords: seismology,time series,data stacking,seismic toolbox
Platform: UNKNOWN
Classifier: Development Status :: 4 - Beta
Classifier: License :: OSI Approved :: MIT License
Classifier: Programming Language :: Python :: 3.7
Requires-Python: >=3.6
License-File: LICENSE.txt
